doxstrux/__init__.py
doxstrux/markdown_parser_core.py
doxstrux/markdown/__init__.py
doxstrux/markdown/budgets.py
doxstrux/markdown/config.py
doxstrux/markdown/exceptions.py
doxstrux/markdown/ir.py
doxstrux/markdown/extractors/__init__.py
doxstrux/markdown/extractors/blockquotes.py
doxstrux/markdown/extractors/codeblocks.py
doxstrux/markdown/extractors/footnotes.py
doxstrux/markdown/extractors/html.py
doxstrux/markdown/extractors/links.py
doxstrux/markdown/extractors/lists.py
doxstrux/markdown/extractors/media.py
doxstrux/markdown/extractors/paragraphs.py
doxstrux/markdown/extractors/sections.py
doxstrux/markdown/extractors/tables.py
doxstrux/markdown/security/__init__.py
doxstrux/markdown/security/validators.py
doxstrux/markdown/utils/__init__.py
doxstrux/markdown/utils/line_utils.py
doxstrux/markdown/utils/text_utils.py
doxstrux/markdown/utils/token_utils.py
doxstrux/md_parser_testing/__init__.py
doxstrux/md_parser_testing/json_utils.py
doxstrux/md_parser_testing/testing_md_parser.py
doxstrux-0.2.1.dist-info/licenses/LICENSE
doxstrux-0.2.1.dist-info/METADATA
doxstrux-0.2.1.dist-info/WHEEL
doxstrux-0.2.1.dist-info/top_level.txt
doxstrux-0.2.1.dist-info/RECORD
