Metadata-Version: 2.4
Name: doxstrux
Version: 0.2.1
Summary: Document structure extraction tool for markdown, with extensibility to PDF and HTML
Author-email: Doxstrux Contributors <doxstrux@example.com>
Maintainer-email: Doxstrux Team <doxstrux@example.com>
License: MIT
Project-URL: Homepage, https://github.com/doxstrux/doxstrux
Project-URL: Documentation, https://doxstrux.readthedocs.io
Project-URL: Repository, https://github.com/doxstrux/doxstrux.git
Project-URL: Issues, https://github.com/doxstrux/doxstrux/issues
Project-URL: Changelog, https://github.com/doxstrux/doxstrux/blob/main/CHANGELOG.md
Keywords: markdown,documentation,analysis,structure-extraction,document-parsing,ai-preprocessing,code-extraction,nested-lists,requirements-extraction
Classifier: Development Status :: 4 - Beta
Classifier: Intended Audience :: Developers
Classifier: Intended Audience :: Science/Research
Classifier: License :: OSI Approved :: MIT License
Classifier: Programming Language :: Python :: 3.12
Classifier: Topic :: Software Development :: Documentation
Classifier: Topic :: Software Development :: Libraries :: Python Modules
Classifier: Topic :: Text Processing :: Markup :: Markdown
Classifier: Operating System :: OS Independent
Classifier: Typing :: Typed
Requires-Python: >=3.12
License-File: LICENSE
Requires-Dist: markdown-it-py>=3.0.0
Requires-Dist: mdit-py-plugins>=0.5.0
Requires-Dist: pyyaml>=6.0.2
Provides-Extra: dev
Requires-Dist: pytest; extra == "dev"
Requires-Dist: pytest-cov; extra == "dev"
Requires-Dist: pytest-asyncio; extra == "dev"
Requires-Dist: pytest-mock; extra == "dev"
Requires-Dist: mypy; extra == "dev"
Requires-Dist: ruff; extra == "dev"
Requires-Dist: black; extra == "dev"
Requires-Dist: bandit; extra == "dev"
Requires-Dist: safety; extra == "dev"
Requires-Dist: mkdocs; extra == "dev"
Requires-Dist: mkdocs-material; extra == "dev"
Requires-Dist: mkdocstrings[python]; extra == "dev"
Requires-Dist: nox; extra == "dev"
Requires-Dist: vulture; extra == "dev"
Requires-Dist: pipreqs; extra == "dev"
Dynamic: license-file
